{"start":"2018-03-01T18:39:16.058Z","end":"2018-03-01T18:39:28.780Z","capabilities":{"maxInstances":5,"browserName":"chrome"},"host":"127.0.0.1","port":4444,"baseUrl":"http://localhost","framework":"mocha","mochaOpts":{"timeout":10000,"ui":"bdd"},"suites":[{"name":"EA SPORTS™ FIFA ONLINE 3","duration":0,"start":"2018-03-01T18:39:22.304Z","tests":[],"hooks":[]},{"name":"EA SPORTS™ FIFA ONLINE 3","duration":2189,"start":"2018-03-01T18:39:22.304Z","end":"2018-03-01T18:39:24.493Z","tests":[{"name":"게임웹 접속","start":"2018-03-01T18:39:22.329Z","end":"2018-03-01T18:39:24.421Z","duration":2092,"state":"pass"},{"name":"openNgmLayer() 실행","start":"2018-03-01T18:39:24.421Z","end":"2018-03-01T18:39:24.492Z","duration":71,"state":"pass"}],"hooks":[{"start":"2018-03-01T18:39:22.326Z","end":"2018-03-01T18:39:22.328Z","duration":2,"title":"\"before all\" hook","associatedSuite":"EA SPORTS™ FIFA ONLINE 3"},{"start":"2018-03-01T18:39:22.329Z","end":"2018-03-01T18:39:22.329Z","duration":0,"title":"\"before each\" hook","associatedSuite":"EA SPORTS™ FIFA ONLINE 3","associatedTest":"게임웹 접속"},{"start":"2018-03-01T18:39:24.421Z","end":"2018-03-01T18:39:24.421Z","duration":0,"title":"\"after each\" hook","associatedSuite":"EA SPORTS™ FIFA ONLINE 3","associatedTest":"게임웹 접속"},{"start":"2018-03-01T18:39:24.421Z","end":"2018-03-01T18:39:24.421Z","duration":0,"title":"\"before each\" hook","associatedSuite":"EA SPORTS™ FIFA ONLINE 3","associatedTest":"openNgmLayer() 실행"},{"start":"2018-03-01T18:39:24.492Z","end":"2018-03-01T18:39:24.492Z","duration":0,"title":"\"after each\" hook","associatedSuite":"EA SPORTS™ FIFA ONLINE 3","associatedTest":"openNgmLayer() 실행"},{"start":"2018-03-01T18:39:24.492Z","end":"2018-03-01T18:39:24.493Z","duration":1,"title":"\"after all\" hook","associatedSuite":"EA SPORTS™ FIFA ONLINE 3"},{"start":"2018-03-01T18:39:24.510Z","end":"2018-03-01T18:39:24.510Z","duration":0,"title":"\"before each\" hook","associatedSuite":"EA SPORTS™ FIFA ONLINE 3","associatedTest":"게임웹 접속"},{"start":"2018-03-01T18:39:26.277Z","end":"2018-03-01T18:39:26.277Z","duration":0,"title":"\"after each\" hook","associatedSuite":"EA SPORTS™ FIFA ONLINE 3","associatedTest":"게임웹 접속"},{"start":"2018-03-01T18:39:26.277Z","end":"2018-03-01T18:39:26.277Z","duration":0,"title":"\"before each\" hook","associatedSuite":"EA SPORTS™ FIFA ONLINE 3","associatedTest":"openNgmLayer() 실행"},{"start":"2018-03-01T18:39:26.367Z","end":"2018-03-01T18:39:26.367Z","duration":0,"title":"\"after each\" hook","associatedSuite":"EA SPORTS™ FIFA ONLINE 3","associatedTest":"openNgmLayer() 실행"},{"start":"2018-03-01T18:39:26.377Z","end":"2018-03-01T18:39:26.377Z","duration":0,"title":"\"before each\" hook","associatedSuite":"EA SPORTS™ FIFA ONLINE 3","associatedTest":"게임웹 접속"},{"start":"2018-03-01T18:39:28.522Z","end":"2018-03-01T18:39:28.522Z","duration":0,"title":"\"after each\" hook","associatedSuite":"EA SPORTS™ FIFA ONLINE 3","associatedTest":"게임웹 접속"},{"start":"2018-03-01T18:39:28.522Z","end":"2018-03-01T18:39:28.522Z","duration":0,"title":"\"before each\" hook","associatedSuite":"EA SPORTS™ FIFA ONLINE 3","associatedTest":"openNgmLayer() 실행"},{"start":"2018-03-01T18:39:28.555Z","end":"2018-03-01T18:39:28.555Z","duration":0,"title":"\"after each\" hook","associatedSuite":"EA SPORTS™ FIFA ONLINE 3","associatedTest":"openNgmLayer() 실행"},{"start":"2018-03-01T18:39:28.564Z","end":"2018-03-01T18:39:28.564Z","duration":0,"title":"\"after all\" hook","associatedSuite":"EA SPORTS™ FIFA ONLINE 3"}]},{"name":"EA SPORTS™ FIFA ONLINE 4","duration":1859,"start":"2018-03-01T18:39:24.509Z","end":"2018-03-01T18:39:26.368Z","tests":[{"name":"게임웹 접속","start":"2018-03-01T18:39:24.509Z","end":"2018-03-01T18:39:26.277Z","duration":1768,"state":"pass"},{"name":"openNgmLayer() 실행","start":"2018-03-01T18:39:26.277Z","end":"2018-03-01T18:39:26.367Z","duration":90,"state":"pass"}],"hooks":[{"start":"2018-03-01T18:39:24.509Z","end":"2018-03-01T18:39:24.509Z","duration":0,"title":"\"before all\" hook","associatedSuite":"EA SPORTS™ FIFA ONLINE 4"},{"start":"2018-03-01T18:39:26.368Z","end":"2018-03-01T18:39:26.368Z","duration":0,"title":"\"after all\" hook","associatedSuite":"EA SPORTS™ FIFA ONLINE 4"}]},{"name":"NEED FOR SPEED™ EDGE","duration":2180,"start":"2018-03-01T18:39:26.376Z","end":"2018-03-01T18:39:28.556Z","tests":[{"name":"게임웹 접속","start":"2018-03-01T18:39:26.377Z","end":"2018-03-01T18:39:28.522Z","duration":2145,"state":"pass"},{"name":"openNgmLayer() 실행","start":"2018-03-01T18:39:28.522Z","end":"2018-03-01T18:39:28.555Z","duration":33,"state":"pass"}],"hooks":[{"start":"2018-03-01T18:39:26.376Z","end":"2018-03-01T18:39:26.377Z","duration":1,"title":"\"before all\" hook","associatedSuite":"NEED FOR SPEED™ EDGE"},{"start":"2018-03-01T18:39:28.556Z","end":"2018-03-01T18:39:28.556Z","duration":0,"title":"\"after all\" hook","associatedSuite":"NEED FOR SPEED™ EDGE"}]}],"state":{"passed":6,"failed":0,"skipped":0}}