{"start":"2018-03-01T20:02:16.743Z","end":"2018-03-01T20:02:31.660Z","capabilities":{"maxInstances":5,"browserName":"chrome"},"host":"127.0.0.1","port":4444,"baseUrl":"http://localhost","framework":"mocha","mochaOpts":{"timeout":10000,"ui":"bdd"},"suites":[{"name":"EA SPORTS™ FIFA ONLINE 3","duration":0,"start":"2018-03-01T20:02:22.910Z","tests":[],"hooks":[]},{"name":"EA SPORTS™ FIFA ONLINE 3","duration":3111,"start":"2018-03-01T20:02:22.910Z","end":"2018-03-01T20:02:26.021Z","tests":[{"name":"게임웹 접속","start":"2018-03-01T20:02:22.913Z","end":"2018-03-01T20:02:25.009Z","duration":2096,"state":"pass"},{"name":"openNgmLayer() 실행","start":"2018-03-01T20:02:25.010Z","end":"2018-03-01T20:02:25.015Z","duration":5,"state":"pass"},{"name":"Ngm Layer 출력여부 확인","start":"2018-03-01T20:02:25.015Z","end":"2018-03-01T20:02:26.008Z","duration":993,"state":"pass"}],"hooks":[{"start":"2018-03-01T20:02:22.911Z","end":"2018-03-01T20:02:22.912Z","duration":1,"title":"\"before all\" hook","associatedSuite":"EA SPORTS™ FIFA ONLINE 3"},{"start":"2018-03-01T20:02:22.913Z","end":"2018-03-01T20:02:22.913Z","duration":0,"title":"\"before each\" hook","associatedSuite":"EA SPORTS™ FIFA ONLINE 3","associatedTest":"게임웹 접속"},{"start":"2018-03-01T20:02:25.009Z","end":"2018-03-01T20:02:25.010Z","duration":1,"title":"\"after each\" hook","associatedSuite":"EA SPORTS™ FIFA ONLINE 3","associatedTest":"게임웹 접속"},{"start":"2018-03-01T20:02:25.010Z","end":"2018-03-01T20:02:25.010Z","duration":0,"title":"\"before each\" hook","associatedSuite":"EA SPORTS™ FIFA ONLINE 3","associatedTest":"openNgmLayer() 실행"},{"start":"2018-03-01T20:02:25.015Z","end":"2018-03-01T20:02:25.015Z","duration":0,"title":"\"after each\" hook","associatedSuite":"EA SPORTS™ FIFA ONLINE 3","associatedTest":"openNgmLayer() 실행"},{"start":"2018-03-01T20:02:25.015Z","end":"2018-03-01T20:02:25.015Z","duration":0,"title":"\"before each\" hook","associatedSuite":"EA SPORTS™ FIFA ONLINE 3","associatedTest":"Ngm Layer 출력여부 확인"},{"start":"2018-03-01T20:02:26.019Z","end":"2018-03-01T20:02:26.019Z","duration":0,"title":"\"after each\" hook","associatedSuite":"EA SPORTS™ FIFA ONLINE 3","associatedTest":"Ngm Layer 출력여부 확인"},{"start":"2018-03-01T20:02:26.019Z","end":"2018-03-01T20:02:26.021Z","duration":2,"title":"\"after all\" hook","associatedSuite":"EA SPORTS™ FIFA ONLINE 3"},{"start":"2018-03-01T20:02:26.037Z","end":"2018-03-01T20:02:26.037Z","duration":0,"title":"\"before each\" hook","associatedSuite":"EA SPORTS™ FIFA ONLINE 3","associatedTest":"게임웹 접속"},{"start":"2018-03-01T20:02:27.881Z","end":"2018-03-01T20:02:27.881Z","duration":0,"title":"\"after each\" hook","associatedSuite":"EA SPORTS™ FIFA ONLINE 3","associatedTest":"게임웹 접속"},{"start":"2018-03-01T20:02:27.881Z","end":"2018-03-01T20:02:27.881Z","duration":0,"title":"\"before each\" hook","associatedSuite":"EA SPORTS™ FIFA ONLINE 3","associatedTest":"openNgmLayer() 실행"},{"start":"2018-03-01T20:02:27.894Z","end":"2018-03-01T20:02:27.894Z","duration":0,"title":"\"after each\" hook","associatedSuite":"EA SPORTS™ FIFA ONLINE 3","associatedTest":"openNgmLayer() 실행"},{"start":"2018-03-01T20:02:27.894Z","end":"2018-03-01T20:02:27.895Z","duration":1,"title":"\"before each\" hook","associatedSuite":"EA SPORTS™ FIFA ONLINE 3","associatedTest":"Ngm Layer 출력여부 확인"},{"start":"2018-03-01T20:02:29.259Z","end":"2018-03-01T20:02:29.259Z","duration":0,"title":"\"after each\" hook","associatedSuite":"EA SPORTS™ FIFA ONLINE 3","associatedTest":"Ngm Layer 출력여부 확인"},{"start":"2018-03-01T20:02:29.272Z","end":"2018-03-01T20:02:29.272Z","duration":0,"title":"\"before each\" hook","associatedSuite":"EA SPORTS™ FIFA ONLINE 3","associatedTest":"게임웹 접속"},{"start":"2018-03-01T20:02:30.489Z","end":"2018-03-01T20:02:30.489Z","duration":0,"title":"\"after each\" hook","associatedSuite":"EA SPORTS™ FIFA ONLINE 3","associatedTest":"게임웹 접속"},{"start":"2018-03-01T20:02:30.489Z","end":"2018-03-01T20:02:30.490Z","duration":1,"title":"\"before each\" hook","associatedSuite":"EA SPORTS™ FIFA ONLINE 3","associatedTest":"openNgmLayer() 실행"},{"start":"2018-03-01T20:02:30.507Z","end":"2018-03-01T20:02:30.507Z","duration":0,"title":"\"after each\" hook","associatedSuite":"EA SPORTS™ FIFA ONLINE 3","associatedTest":"openNgmLayer() 실행"},{"start":"2018-03-01T20:02:30.507Z","end":"2018-03-01T20:02:30.507Z","duration":0,"title":"\"before each\" hook","associatedSuite":"EA SPORTS™ FIFA ONLINE 3","associatedTest":"Ngm Layer 출력여부 확인"},{"start":"2018-03-01T20:02:31.432Z","end":"2018-03-01T20:02:31.432Z","duration":0,"title":"\"after each\" hook","associatedSuite":"EA SPORTS™ FIFA ONLINE 3","associatedTest":"Ngm Layer 출력여부 확인"},{"start":"2018-03-01T20:02:31.441Z","end":"2018-03-01T20:02:31.441Z","duration":0,"title":"\"after all\" hook","associatedSuite":"EA SPORTS™ FIFA ONLINE 3"}]},{"name":"EA SPORTS™ FIFA ONLINE 4","duration":3225,"start":"2018-03-01T20:02:26.036Z","end":"2018-03-01T20:02:29.261Z","tests":[{"name":"게임웹 접속","start":"2018-03-01T20:02:26.036Z","end":"2018-03-01T20:02:27.881Z","duration":1845,"state":"pass"},{"name":"openNgmLayer() 실행","start":"2018-03-01T20:02:27.881Z","end":"2018-03-01T20:02:27.894Z","duration":13,"state":"pass"},{"name":"Ngm Layer 출력여부 확인","start":"2018-03-01T20:02:27.894Z","end":"2018-03-01T20:02:29.250Z","duration":1356,"state":"pass"}],"hooks":[{"start":"2018-03-01T20:02:26.036Z","end":"2018-03-01T20:02:26.036Z","duration":0,"title":"\"before all\" hook","associatedSuite":"EA SPORTS™ FIFA ONLINE 4"},{"start":"2018-03-01T20:02:29.259Z","end":"2018-03-01T20:02:29.261Z","duration":2,"title":"\"after all\" hook","associatedSuite":"EA SPORTS™ FIFA ONLINE 4"}]},{"name":"NEED FOR SPEED™ EDGE","duration":2162,"start":"2018-03-01T20:02:29.271Z","end":"2018-03-01T20:02:31.433Z","tests":[{"name":"게임웹 접속","start":"2018-03-01T20:02:29.272Z","end":"2018-03-01T20:02:30.489Z","duration":1217,"state":"pass"},{"name":"openNgmLayer() 실행","start":"2018-03-01T20:02:30.489Z","end":"2018-03-01T20:02:30.507Z","duration":18,"state":"pass"},{"name":"Ngm Layer 출력여부 확인","start":"2018-03-01T20:02:30.507Z","end":"2018-03-01T20:02:31.418Z","duration":911,"state":"pass"}],"hooks":[{"start":"2018-03-01T20:02:29.271Z","end":"2018-03-01T20:02:29.271Z","duration":0,"title":"\"before all\" hook","associatedSuite":"NEED FOR SPEED™ EDGE"},{"start":"2018-03-01T20:02:31.432Z","end":"2018-03-01T20:02:31.433Z","duration":1,"title":"\"after all\" hook","associatedSuite":"NEED FOR SPEED™ EDGE"}]}],"state":{"passed":9,"failed":0,"skipped":0}}